pybus/__init__.py
pybus/core/__init__.py
pybus/core/message.py
pybus/core/messagebus.py
pybus/default/__init__.py
pybus/default/messagebus.py
py_bus-0.2.0.dist-info/WHEEL
py_bus-0.2.0.dist-info/METADATA
py_bus-0.2.0.dist-info/RECORD
